robot_inspector
robot_logger
