Metadata-Version: 2.1
Name: sql-robot-logger
Version: 0.1.1
Summary: A sql robot logger
Home-page: https://github.com/adamhamden/sql_robot_logger
Author: Adam Hamden
Author-email: ahamden@usc.edu
License: MIT
Platform: UNKNOWN
Classifier: License :: OSI Approved :: MIT License
Classifier: Programming Language :: Python
Classifier: Programming Language :: Python :: 3
Classifier: Programming Language :: Python :: 3.6
Classifier: Programming Language :: Python :: Implementation :: CPython
Classifier: Programming Language :: Python :: Implementation :: PyPy
Requires-Python: >=3.6.0
